Workbook

Sheet Описание
A1: FUTUREWISE — финансовая модель (B2B2C, white-label модуль для банков)
A3: Как устроена модель
A4: FUTUREWISE встраивается в мобильное приложение банка перед оформлением рассрочки, BNPL или кредита.
A5: Банк платит за разовую интеграцию и ежемесячно за каждого активного пользователя модуля.
A7: Листы
A8: Допущения — все входные параметры. Меняйте только их, остальное пересчитается.
A9: Рынок — TAM / SAM / SOM на опубликованных данных (источники указаны рядом с каждой цифрой).
A10: P&L — выручка, расходы и результат по годам 2027–2029.
A11: Эффект для банка — сколько банк экономит на просрочке по сравнению с ценой лицензии.
A12: Чувствительность — выручка 3-го года при разной цене и доле использования.
A14: Обозначения
A15: Синий текст — вводимое значение. Жёлтая заливка — ключевое допущение. Чёрный — формула. Зелёный — ссылка на другой лист.
... A19: их нужно проверить пилотом с банком. Модель не является прогнозом.

Sheet Допущения
A1: Допущения
A3: Параметр | B3: 2027 | C3: 2028 | D3: 2029 | E3: Комментарий / источник
A4: Банков-партнёров на конец года | B4: 1 | C4: 3 | D4: 6 | E4: Допущение: пилот с одним банком, затем расширение
A5: MAU мобильного приложения одного банка, чел. | B5: 3000000 | C5: 3000000 | D5: 3000000 | E5: Допущение: средний партнёр из топ-20 банков
A6: Доля MAU, открывающих краш-тест за месяц | B6: 0.02 | C6: 0.03 | D6: 0.04 | E6: Допущение: проверить на пилоте
A7: Цена за активного пользователя в месяц, ₽ | B7: 15 | C7: 15 | D7: 15 | E7: Допущение: цена лицензии
A8: Разовая интеграция на нового банка, ₽ | B8: 3000000 | C8: 3000000 | D8: 3000000 | E8: Допущение: white-label + SDK + сопровождение запуска
A9: Команда (ФОТ с налогами), ₽ в год | B9: 18000000 | C9: 30000000 | D9: 42000000 | E9: Допущение: 6 → 10 → 14 человек
A10: Инфраструктура на активного пользователя в месяц, ₽ | B10: 0.5 | C10: 0.5 | D10: 0.5 | E10: Допущение: расчёт идёт на устройстве, сервер только отдаёт приложение
A11: Продажи и маркетинг, % выручки | B11: 0.15 | C11: 0.15 | D11: 0.15 | E11: Допущение: B2B-продажи в банки
A12: Налог на прибыль | B12: 0.05 | C12: 0.05 | D12: 0.05 | E12: Ставка для аккредитованных ИТ-компаний с 2025 г. (НК РФ, ст. 284)
A15: Эффект для банка (допущения)
A16: Доля активных пользователей, принимающих крупное решение в месяц | B16: 0.3 | E16: Допущение
A17: Доля из них, кто выбрал более безопасный вариант после теста | B17: 0.15 | E17: Допущение: проверить на пилоте
A18: Средний чек покупки частями, ₽ | B18: 12000 | E18: Infoline-аналитика: 12 000 ₽ у активных пользователей (retail.ru / Т—Ж, 2025)
A19: Доля плохих долгов в BNPL | B19: 0.034 | E19: Обзор Банка России за 2025 г. (РИА Новости, 01.06.2026)

Sheet Рынок
A1: Оценка рынка (Россия)
A3: Показатель | B3: Значение | C3: Источник
A4: Заёмщиков — физлиц в БКИ, чел. (1 п/г 2025) | B4: 49700000 | C4: Банк России, информационный материал о БКИ за 1 п/г 2025: cbr.ru/Collection/Collection/File/59477/inf-material_bki_2025fh.pdf
A5: Уникальных пользователей BNPL, чел. (янв.–сент. 2025) | B5: 36000000 | C5: Т2 для «Ведомостей», 29.10.2025 (retail.ru)
A6: Ежемесячная аудитория BNPL, чел. (сент. 2025) | B6: 3900000 | C6: Т2 для «Ведомостей», 29.10.2025 (retail.ru)
A7: Выдачи BNPL за 2025 г., ₽ | B7: 500000000000 | C7: Обзор Банка России, рост +80% г/г (РИА Новости / investfuture.ru, 01.06.2026)
A8: Задолженность по BNPL, ₽ | B8: 100000000000 | C8: Там же, +40% г/г
A10: Доля пользователей BNPL, у которых есть смысл проверять решение | B10: 0.25 | C10: Допущение: регулярные покупки частями на заметные суммы
A12: Оценка, ₽ в год | B12: Значение | C12: Как считается
A13: TAM — все заёмщики пользуются модулем | B13: =B4*12*Допущения!$B$7 -> 8946000000 | C13: Заёмщики × 12 мес. × цена за пользователя
A14: SAM — пользователи BNPL с регулярными покупками | B14: =B5*B10*12*Допущения!$B$7 -> 1620000000 | C14: Пользователи BNPL × доля × 12 мес. × цена
A15: SOM — выручка FUTUREWISE в 2029 г. | B15: ='P&L'!D8 -> 138600000 | C15: Из листа P&L
A16: Доля SOM в SAM | B16: =IFERROR(B15/B14,0) -> 0.085555556

Sheet P&L
A1: P&L, ₽
A3: Статья | B3: 2027 | C3: 2028 | D3: 2029
A4: Банков-партнёров | B4: =Допущения!$B$4 -> 1 | C4: =Допущения!$C$4 -> 3 | D4: =Допущения!$D$4 -> 6
A5: Новых банков за год | B5: =Допущения!$B$4 -> 1 | C5: =Допущения!$C$4-Допущения!$B$4 -> 2 | D5: =Допущения!$D$4-Допущения!$C$4 -> 3
A6: Активных пользователей в месяц | B6: =B4*Допущения!$B$5*Допущения!$B$6 -> 60000 | C6: =C4*Допущения!$C$5*Допущения!$C$6 -> 270000 | D6: =D4*Допущения!$D$5*Допущения!$D$6 -> 720000
A7: Выручка: интеграции | B7: =B5*Допущения!$B$8 -> 3000000 | C7: =C5*Допущения!$C$8 -> 6000000 | D7: =D5*Допущения!$D$8 -> 9000000
A8: Выручка: всего | B8: =B6*Допущения!$B$7*12+B7 -> 13800000 | C8: =C6*Допущения!$C$7*12+C7 -> 54600000 | D8: =D6*Допущения!$D$7*12+D7 -> 138600000
A9: в т.ч. лицензии | B9: =B8-B7 -> 10800000 | C9: =C8-C7 -> 48600000 | D9: =D8-D7 -> 129600000
A10: Расходы
A11: Команда | B11: =Допущения!$B$9 -> 18000000 | C11: =Допущения!$C$9 -> 30000000 | D11: =Допущения!$D$9 -> 42000000
A12: Инфраструктура | B12: =B6*Допущения!$B$10*12 -> 360000 | C12: =C6*Допущения!$C$10*12 -> 1620000 | D12: =D6*Допущения!$D$10*12 -> 4320000
A13: Продажи и маркетинг | B13: =B8*Допущения!$B$11 -> 2070000 | C13: =C8*Допущения!$C$11 -> 8190000 | D13: =D8*Допущения!$D$11 -> 20790000
A14: Расходы: всего | B14: =SUM(B11:B13) -> 20430000 | C14: =SUM(C11:C13) -> 39810000 | D14: =SUM(D11:D13) -> 67110000
A16: EBITDA | B16: =B8-B14 -> -6630000 | C16: =C8-C14 -> 14790000 | D16: =D8-D14 -> 71490000
A17: Рентабельность EBITDA | B17: =IFERROR(B16/B8,0) -> -0.48043478 | C17: =IFERROR(C16/C8,0) -> 0.27087912 | D17: =IFERROR(D16/D8,0) -> 0.51580087
A18: Налог на прибыль | B18: =MAX(0,B16)*Допущения!$B$12 -> 0 | C18: =MAX(0,C16)*Допущения!$C$12 -> 739500 | D18: =MAX(0,D16)*Допущения!$D$12 -> 3574500
A19: Чистая прибыль | B19: =B16-B18 -> -6630000 | C19: =C16-C18 -> 14050500 | D19: =D16-D18 -> 67915500
A20: Накопленный результат | B20: =B19 -> -6630000 | C20: =B20+C19 -> 7420500 | D20: =C20+D19 -> 75336000
A22: Безубыточность по EBITDA достигается в году, где EBITDA > 0. Все значения пересчитываются из листа «Допущения».

Sheet Эффект для банка
A1: Эффект для одного банка-партнёра, ₽ в год (по допущениям 2028 г.)
A3: Показатель | B3: Значение | C3: Как считается
A4: Активных пользователей модуля в месяц | B4: =Допущения!$C$5*Допущения!$C$6 -> 90000 | C4: MAU × доля использования
A5: Решений, пересмотренных в пользу безопасного варианта, в год | B5: =B4*Допущения!$B$16*Допущения!$B$17*12 -> 48600 | C5: × доля решений × доля изменивших × 12
A6: Объём рискованного долга, который не возник, ₽ | B6: =B5*Допущения!$B$18 -> 583200000 | C6: × средний чек
A7: Сэкономленные потери по плохим долгам, ₽ | B7: =B6*Допущения!$B$19 -> 19828800 | C7: × доля плохих долгов
A8: Стоимость лицензии для банка, ₽ | B8: =B4*Допущения!$C$7*12 -> 16200000 | C8: активные пользователи × цена × 12
A9: Экономия на 1 ₽ лицензии | B9: =IFERROR(B7/B8,0) -> 1.224 | C9: Окупаемость только по потерям, без учёта лояльности и NPS
A11: Это иллюстрация на допущениях. Реальный эффект измеряется A/B-тестом на пилоте: просрочка у тех, кто прошёл краш-тест, против контрольной группы.

Sheet Чувствительность
A1: Выручка от лицензий в 2029 г., млн ₽
A2: Строки — цена за пользователя в месяц, столбцы — доля MAU, открывающих краш-тест. Банков и MAU — из листа «Допущения» (2029).
A4: Цена, ₽ \ доля MAU | B4: 0.01 | C4: 0.02 | D4: 0.03 | E4: 0.04 | F4: 0.06
A5: 5 | B5: =Допущения!$D$4*Допущения!$D$5*B$4*$A5*12/1000000 -> 10.8 | C5: =Допущения!$D$4*Допущения!$D$5*C$4*$A5*12/1000000 -> 21.6 | D5: =Допущения!$D$4*Допущения!$D$5*D$4*$A5*12/1000000 -> 32.4 | E5: =Допущения!$D$4*Допущения!$D$5*E$4*$A5*12/1000000 -> 43.2 | F5: =Допущения!$D$4*Допущения!$D$5*F$4*$A5*12/1000000 -> 64.8
A6: 10 | B6: =Допущения!$D$4*Допущения!$D$5*B$4*$A6*12/1000000 -> 21.6 | C6: =Допущения!$D$4*Допущения!$D$5*C$4*$A6*12/1000000 -> 43.2 | D6: =Допущения!$D$4*Допущения!$D$5*D$4*$A6*12/1000000 -> 64.8 | E6: =Допущения!$D$4*Допущения!$D$5*E$4*$A6*12/1000000 -> 86.4 | F6: =Допущения!$D$4*Допущения!$D$5*F$4*$A6*12/1000000 -> 129.6
A7: 15 | B7: =Допущения!$D$4*Допущения!$D$5*B$4*$A7*12/1000000 -> 32.4 | C7: =Допущения!$D$4*Допущения!$D$5*C$4*$A7*12/1000000 -> 64.8 | D7: =Допущения!$D$4*Допущения!$D$5*D$4*$A7*12/1000000 -> 97.2 | E7: =Допущения!$D$4*Допущения!$D$5*E$4*$A7*12/1000000 -> 129.6 | F7: =Допущения!$D$4*Допущения!$D$5*F$4*$A7*12/1000000 -> 194.4
A8: 20 | B8: =Допущения!$D$4*Допущения!$D$5*B$4*$A8*12/1000000 -> 43.2 | C8: =Допущения!$D$4*Допущения!$D$5*C$4*$A8*12/1000000 -> 86.4 | D8: =Допущения!$D$4*Допущения!$D$5*D$4*$A8*12/1000000 -> 129.6 | E8: =Допущения!$D$4*Допущения!$D$5*E$4*$A8*12/1000000 -> 172.8 | F8: =Допущения!$D$4*Допущения!$D$5*F$4*$A8*12/1000000 -> 259.2
A9: 30 | B9: =Допущения!$D$4*Допущения!$D$5*B$4*$A9*12/1000000 -> 64.8 | C9: =Допущения!$D$4*Допущения!$D$5*C$4*$A9*12/1000000 -> 129.6 | D9: =Допущения!$D$4*Допущения!$D$5*D$4*$A9*12/1000000 -> 194.4 | E9: =Допущения!$D$4*Допущения!$D$5*E$4*$A9*12/1000000 -> 259.2 | F9: =Допущения!$D$4*Допущения!$D$5*F$4*$A9*12/1000000 -> 388.8
